{"items":[{"t":"F","n":"\\is_valid_xml","p":"[Global_Namespace].html#function_is_valid_xml","d":"<p>Check if a string is valid XML.</p>"},{"t":"F","n":"\\validate_xml","p":"[Global_Namespace].html#function_validate_xml","d":"<p>Validate XML string.</p>"},{"t":"F","n":"\\xml_decode","p":"[Global_Namespace].html#function_xml_decode","d":"<p>Convert a string of XML into an array.</p>"},{"t":"F","n":"\\xml_encode","p":"[Global_Namespace].html#function_xml_encode","d":"<p>Convert the an array to an xml string.</p>"},{"t":"C","n":"Bmatovu\\LaravelXml\\Http\\Middleware\\RequireXml","p":"Bmatovu/LaravelXml/Http/Middleware/RequireXml.html","d":null,"f":{"n":"Bmatovu\\LaravelXml\\Http\\Middleware","p":"Bmatovu/LaravelXml/Http/Middleware.html"}},{"t":"C","n":"Bmatovu\\LaravelXml\\Http\\XmlResponse","p":"Bmatovu/LaravelXml/Http/XmlResponse.html","d":null,"f":{"n":"Bmatovu\\LaravelXml\\Http","p":"Bmatovu/LaravelXml/Http.html"}},{"t":"C","n":"Bmatovu\\LaravelXml\\LaravelXml","p":"Bmatovu/LaravelXml/LaravelXml.html","d":null,"f":{"n":"Bmatovu\\LaravelXml","p":"Bmatovu/LaravelXml.html"}},{"t":"C","n":"Bmatovu\\LaravelXml\\LaravelXmlServiceProvider","p":"Bmatovu/LaravelXml/LaravelXmlServiceProvider.html","d":null,"f":{"n":"Bmatovu\\LaravelXml","p":"Bmatovu/LaravelXml.html"}},{"t":"C","n":"Bmatovu\\LaravelXml\\Support\\ArrayToXml","p":"Bmatovu/LaravelXml/Support/ArrayToXml.html","d":"","f":{"n":"Bmatovu\\LaravelXml\\Support","p":"Bmatovu/LaravelXml/Support.html"}},{"t":"C","n":"Bmatovu\\LaravelXml\\Support\\Facades\\LaravelXml","p":"Bmatovu/LaravelXml/Support/Facades/LaravelXml.html","d":null,"f":{"n":"Bmatovu\\LaravelXml\\Support\\Facades","p":"Bmatovu/LaravelXml/Support/Facades.html"}},{"t":"C","n":"Bmatovu\\LaravelXml\\Support\\JsonSimpleXMLElementDecorator","p":"Bmatovu/LaravelXml/Support/JsonSimpleXMLElementDecorator.html","d":"<p>Class JsonSimpleXMLElementDecorator.</p>","f":{"n":"Bmatovu\\LaravelXml\\Support","p":"Bmatovu/LaravelXml/Support.html"}},{"t":"C","n":"Bmatovu\\LaravelXml\\Support\\XmlElement","p":"Bmatovu/LaravelXml/Support/XmlElement.html","d":null,"f":{"n":"Bmatovu\\LaravelXml\\Support","p":"Bmatovu/LaravelXml/Support.html"}},{"t":"C","n":"Bmatovu\\LaravelXml\\Support\\XmlValidator","p":"Bmatovu/LaravelXml/Support/XmlValidator.html","d":"<p>Class XmlValidator.</p>","f":{"n":"Bmatovu\\LaravelXml\\Support","p":"Bmatovu/LaravelXml/Support.html"}},{"t":"M","n":"Bmatovu\\LaravelXml\\Http\\Middleware\\RequireXml::handle","p":"Bmatovu/LaravelXml/Http/Middleware/RequireXml.html#method_handle","d":"<p>Handle an incoming request.</p>"},{"t":"M","n":"Bmatovu\\LaravelXml\\Http\\XmlResponse::__construct","p":"Bmatovu/LaravelXml/Http/XmlResponse.html#method___construct","d":"Constructor."},{"t":"M","n":"Bmatovu\\LaravelXml\\Http\\XmlResponse::setContent","p":"Bmatovu/LaravelXml/Http/XmlResponse.html#method_setContent","d":"<p>Set the content on the response.</p>"},{"t":"M","n":"Bmatovu\\LaravelXml\\LaravelXml::getFacadeAccessor","p":"Bmatovu/LaravelXml/LaravelXml.html#method_getFacadeAccessor","d":"<p>Get the binding in the IoC container.</p>"},{"t":"M","n":"Bmatovu\\LaravelXml\\LaravelXmlServiceProvider::boot","p":"Bmatovu/LaravelXml/LaravelXmlServiceProvider.html#method_boot","d":"<p>Bootstrap the application services.</p>"},{"t":"M","n":"Bmatovu\\LaravelXml\\LaravelXmlServiceProvider::register","p":"Bmatovu/LaravelXml/LaravelXmlServiceProvider.html#method_register","d":"<p>Register the application services.</p>"},{"t":"M","n":"Bmatovu\\LaravelXml\\Support\\ArrayToXml::__construct","p":"Bmatovu/LaravelXml/Support/ArrayToXml.html#method___construct","d":"<p>Construct a new instance.</p>"},{"t":"M","n":"Bmatovu\\LaravelXml\\Support\\ArrayToXml::convert","p":"Bmatovu/LaravelXml/Support/ArrayToXml.html#method_convert","d":"<p>Convert the given array to an xml string.</p>"},{"t":"M","n":"Bmatovu\\LaravelXml\\Support\\ArrayToXml::toXml","p":"Bmatovu/LaravelXml/Support/ArrayToXml.html#method_toXml","d":"<p>Return as XML.</p>"},{"t":"M","n":"Bmatovu\\LaravelXml\\Support\\ArrayToXml::toDom","p":"Bmatovu/LaravelXml/Support/ArrayToXml.html#method_toDom","d":"<p>Return as DOM object.</p>"},{"t":"M","n":"Bmatovu\\LaravelXml\\Support\\ArrayToXml::addNode","p":"Bmatovu/LaravelXml/Support/ArrayToXml.html#method_addNode","d":"<p>Add node.</p>"},{"t":"M","n":"Bmatovu\\LaravelXml\\Support\\ArrayToXml::addCollectionNode","p":"Bmatovu/LaravelXml/Support/ArrayToXml.html#method_addCollectionNode","d":"<p>Add collection node.</p>"},{"t":"M","n":"Bmatovu\\LaravelXml\\Support\\ArrayToXml::addSequentialNode","p":"Bmatovu/LaravelXml/Support/ArrayToXml.html#method_addSequentialNode","d":"<p>Add sequential node.</p>"},{"t":"M","n":"Bmatovu\\LaravelXml\\Support\\ArrayToXml::isArrayAllKeySequential","p":"Bmatovu/LaravelXml/Support/ArrayToXml.html#method_isArrayAllKeySequential","d":"<p>Check if all array keys are sequential.</p>"},{"t":"M","n":"Bmatovu\\LaravelXml\\Support\\ArrayToXml::addAttributes","p":"Bmatovu/LaravelXml/Support/ArrayToXml.html#method_addAttributes","d":"<p>Add attributes.</p>"},{"t":"M","n":"Bmatovu\\LaravelXml\\Support\\ArrayToXml::createRootElement","p":"Bmatovu/LaravelXml/Support/ArrayToXml.html#method_createRootElement","d":"<p>Create the root element.</p>"},{"t":"M","n":"Bmatovu\\LaravelXml\\Support\\ArrayToXml::convertElement","p":"Bmatovu/LaravelXml/Support/ArrayToXml.html#method_convertElement","d":"<p>Parse individual element.</p>"},{"t":"M","n":"Bmatovu\\LaravelXml\\Support\\Facades\\LaravelXml::__construct","p":"Bmatovu/LaravelXml/Support/Facades/LaravelXml.html#method___construct","d":null},{"t":"M","n":"Bmatovu\\LaravelXml\\Support\\Facades\\LaravelXml::encode","p":"Bmatovu/LaravelXml/Support/Facades/LaravelXml.html#method_encode","d":"<p>Convert the an array to an xml string.</p>"},{"t":"M","n":"Bmatovu\\LaravelXml\\Support\\Facades\\LaravelXml::decode","p":"Bmatovu/LaravelXml/Support/Facades/LaravelXml.html#method_decode","d":"<p>Convert a string of XML into an array.</p>"},{"t":"M","n":"Bmatovu\\LaravelXml\\Support\\Facades\\LaravelXml::is_valid","p":"Bmatovu/LaravelXml/Support/Facades/LaravelXml.html#method_is_valid","d":"<p>Check if a string is valid XML.</p>"},{"t":"M","n":"Bmatovu\\LaravelXml\\Support\\Facades\\LaravelXml::validate","p":"Bmatovu/LaravelXml/Support/Facades/LaravelXml.html#method_validate","d":"<p>Validate XML string.</p>"},{"t":"M","n":"Bmatovu\\LaravelXml\\Support\\JsonSimpleXMLElementDecorator::__construct","p":"Bmatovu/LaravelXml/Support/JsonSimpleXMLElementDecorator.html#method___construct","d":"Constructor."},{"t":"M","n":"Bmatovu\\LaravelXml\\Support\\JsonSimpleXMLElementDecorator::useAttributes","p":"Bmatovu/LaravelXml/Support/JsonSimpleXMLElementDecorator.html#method_useAttributes","d":"<p>Should use attributes.</p>"},{"t":"M","n":"Bmatovu\\LaravelXml\\Support\\JsonSimpleXMLElementDecorator::useText","p":"Bmatovu/LaravelXml/Support/JsonSimpleXMLElementDecorator.html#method_useText","d":"<p>Should use text.</p>"},{"t":"M","n":"Bmatovu\\LaravelXml\\Support\\JsonSimpleXMLElementDecorator::setDepth","p":"Bmatovu/LaravelXml/Support/JsonSimpleXMLElementDecorator.html#method_setDepth","d":"<p>Set depth.</p>"},{"t":"M","n":"Bmatovu\\LaravelXml\\Support\\JsonSimpleXMLElementDecorator::jsonSerialize","p":"Bmatovu/LaravelXml/Support/JsonSimpleXMLElementDecorator.html#method_jsonSerialize","d":"<p>Specify data which should be serialized to JSON.</p>"},{"t":"M","n":"Bmatovu\\LaravelXml\\Support\\XmlElement::get","p":"Bmatovu/LaravelXml/Support/XmlElement.html#method_get","d":"<p>Provides access to element's children.</p>"},{"t":"M","n":"Bmatovu\\LaravelXml\\Support\\XmlValidator::__construct","p":"Bmatovu/LaravelXml/Support/XmlValidator.html#method___construct","d":"Constructor."},{"t":"M","n":"Bmatovu\\LaravelXml\\Support\\XmlValidator::is_valid","p":"Bmatovu/LaravelXml/Support/XmlValidator.html#method_is_valid","d":"<p>Check if a string is valid XML.</p>"},{"t":"M","n":"Bmatovu\\LaravelXml\\Support\\XmlValidator::validate","p":"Bmatovu/LaravelXml/Support/XmlValidator.html#method_validate","d":"<p>Validate XML string.</p>"},{"t":"M","n":"Bmatovu\\LaravelXml\\Support\\XmlValidator::getElement","p":"Bmatovu/LaravelXml/Support/XmlValidator.html#method_getElement","d":"<p>Get element from message.</p>"},{"t":"M","n":"Bmatovu\\LaravelXml\\Support\\XmlValidator::getMessage","p":"Bmatovu/LaravelXml/Support/XmlValidator.html#method_getMessage","d":"<p>Get refined message.</p>"},{"t":"N","n":"","p":"[Global_Namespace].html"},{"t":"N","n":"Bmatovu","p":"Bmatovu.html"},{"t":"N","n":"Bmatovu\\LaravelXml","p":"Bmatovu/LaravelXml.html"},{"t":"N","n":"Bmatovu\\LaravelXml\\Http","p":"Bmatovu/LaravelXml/Http.html"},{"t":"N","n":"Bmatovu\\LaravelXml\\Http\\Middleware","p":"Bmatovu/LaravelXml/Http/Middleware.html"},{"t":"N","n":"Bmatovu\\LaravelXml\\Support","p":"Bmatovu/LaravelXml/Support.html"},{"t":"N","n":"Bmatovu\\LaravelXml\\Support\\Facades","p":"Bmatovu/LaravelXml/Support/Facades.html"}]}
